[{
    "name": "Shandy Sweetlove",
    "email": "ssweetlove0@surveymonkey.com",
    "gender": "Male",
    "job": "chef",
    "favourite_colours": "blue",
    "avatar": "https://robohash.org/consequunturtemporeid.png?size=50x50&set=set1"
  }, {
    "name": "Miguelita Blackston",
    "email": "mblackston1@businesswire.com",
    "gender": "Male",
    "job": "trader",
    "favourite_colours": "red",
    "avatar": "https://robohash.org/voluptatemcorporisalias.jpg?size=50x50&set=set1"
  }, {
    "name": "Amalie Tunbridge",
    "email": "atunbridge2@sourceforge.net",
    "gender": "Female",
    "job": "CEO",
    "favourite_colours": "red",
    "avatar": "https://robohash.org/etoditdolorum.jpg?size=50x50&set=set1"
  }, {
    "name": "Alan Shears",
    "email": "ashears3@thetimes.co.uk",
    "gender": "Female",
    "job": "chef",
    "favourite_colours": "green",
    "avatar": "https://robohash.org/errormaioressoluta.png?size=50x50&set=set1"
  }, {
    "name": "Werner Bleasdale",
    "email": "wbleasdale4@princeton.edu",
    "gender": "Female",
    "job": "trader",
    "favourite_colours": "yellow",
    "avatar": "https://robohash.org/pariatursedveniam.png?size=50x50&set=set1"
  }, {
    "name": "Barnabe Lorant",
    "email": "blorant5@ucla.edu",
    "gender": "Female",
    "job": "coder",
    "favourite_colours": "blue",
    "avatar": "https://robohash.org/possimusnullaquam.jpg?size=50x50&set=set1"
  }, {
    "name": "Barbabra Lemmon",
    "email": "blemmon6@nyu.edu",
    "gender": "Male",
    "job": "CEO",
    "favourite_colours": "red",
    "avatar": "https://robohash.org/delectusinvelit.jpg?size=50x50&set=set1"
  }, {
    "name": "Solly Georghiou",
    "email": "sgeorghiou7@sourceforge.net",
    "gender": "Female",
    "job": "chef",
    "favourite_colours": "violet",
    "avatar": "https://robohash.org/etanimidebitis.jpg?size=50x50&set=set1"
  }, {
    "name": "Joice Sloy",
    "email": "jsloy8@baidu.com",
    "gender": "Female",
    "job": "trader",
    "favourite_colours": "red",
    "avatar": "https://robohash.org/officiisquiasequi.png?size=50x50&set=set1"
  }, {
    "name": "Thaxter Staddom",
    "email": "tstaddom9@bravesites.com",
    "gender": "Female",
    "job": "chef",
    "favourite_colours": "green",
    "avatar": "https://robohash.org/etquaeratautem.bmp?size=50x50&set=set1"
  }, {
    "name": "Domeniga Calafate",
    "email": "dcalafatea@opera.com",
    "gender": "Female",
    "job": "chef",
    "favourite_colours": "green",
    "avatar": "https://robohash.org/estomniseos.jpg?size=50x50&set=set1"
  }, {
    "name": "Stephine Ravilus",
    "email": "sravilusb@home.pl",
    "gender": "Female",
    "job": "trader",
    "favourite_colours": "violet",
    "avatar": "https://robohash.org/utfugiatad.png?size=50x50&set=set1"
  }, {
    "name": "Hurlee Sondland",
    "email": "hsondlandc@so-net.ne.jp",
    "gender": "Male",
    "job": "real estate agent",
    "favourite_colours": "blue",
    "avatar": "https://robohash.org/adipisciporropraesentium.bmp?size=50x50&set=set1"
  }, {
    "name": "Arlen Inett",
    "email": "ainettd@geocities.com",
    "gender": "Female",
    "job": "CEO",
    "favourite_colours": "orange",
    "avatar": "https://robohash.org/dolorequodnatus.jpg?size=50x50&set=set1"
  }, {
    "name": "Halimeda Bouda",
    "email": "hboudae@jugem.jp",
    "gender": "Female",
    "job": "chef",
    "favourite_colours": "violet",
    "avatar": "https://robohash.org/liberoexcepturivel.png?size=50x50&set=set1"
  }, {
    "name": "Hyacinth Streat",
    "email": "hstreatf@microsoft.com",
    "gender": "Female",
    "job": "coder",
    "favourite_colours": "blue",
    "avatar": "https://robohash.org/velitconsequaturconsequuntur.jpg?size=50x50&set=set1"
  }, {
    "name": "Wang Digges",
    "email": "wdiggesg@answers.com",
    "gender": "Male",
    "job": "CEO",
    "favourite_colours": "blue",
    "avatar": "https://robohash.org/eumeoset.jpg?size=50x50&set=set1"
  }, {
    "name": "Tamarah Stenning",
    "email": "tstenningh@mediafire.com",
    "gender": "Male",
    "job": "trader",
    "favourite_colours": "blue",
    "avatar": "https://robohash.org/quoplaceatid.bmp?size=50x50&set=set1"
  }, {
    "name": "Amargo Fulger",
    "email": "afulgeri@nytimes.com",
    "gender": "Male",
    "job": "real estate agent",
    "favourite_colours": "blue",
    "avatar": "https://robohash.org/autquibusdamenim.jpg?size=50x50&set=set1"
  }, {
    "name": "Aleen MacCarlich",
    "email": "amaccarlichj@cocolog-nifty.com",
    "gender": "Female",
    "job": "trader",
    "favourite_colours": "green",
    "avatar": "https://robohash.org/sitexcepturivoluptatem.png?size=50x50&set=set1"
  }]